redis_heartbeat_lock/__init__.py
redis_heartbeat_lock/async_lock.py
redis_heartbeat_lock/context_manager.py
redis_heartbeat_lock/executor.py
redis_heartbeat_lock/py.typed
redis_heartbeat_lock/shared.py
redis_heartbeat_lock-0.1.16.dist-info/LICENSE
redis_heartbeat_lock-0.1.16.dist-info/WHEEL
redis_heartbeat_lock-0.1.16.dist-info/METADATA
redis_heartbeat_lock-0.1.16.dist-info/RECORD
