Metadata-Version: 2.1
Name: redis-heartbeat-lock
Version: 0.1.16
Summary: Top-level package for Redis heartbeat lock.
Home-page: https://github.com/fwallacevt/redis-heartbeat-lock
License: MIT
Author: Forrest Wallace
Author-email: forrest.wallace.vt@gmail.com
Requires-Python: >=3.7,<4.0
Classifier: Development Status :: 2 - Pre-Alpha
Classifier: Intended Audience :: Developers
Classifier: License :: OSI Approved :: MIT License
Classifier: Natural Language :: English
Classifier: Programming Language :: Python :: 3
Classifier: Programming Language :: Python :: 3.7
Classifier: Programming Language :: Python :: 3.8
Requires-Dist: redis
